basiccalculator/__init__.py
basiccalculator/main.py
basiccalculator_tahasin-0.0.1.dist-info/METADATA
basiccalculator_tahasin-0.0.1.dist-info/WHEEL
basiccalculator_tahasin-0.0.1.dist-info/top_level.txt
basiccalculator_tahasin-0.0.1.dist-info/RECORD
