Metadata-Version: 2.4
Name: basiccalculator-tahasin
Version: 0.0.1
Summary: A very basic calculator
Dynamic: summary
